{
    "schemes": [
        "http"
    ],
    "swagger": "2.0",
    "info": {
        "description": "A server for BirdAI API, for managing users, admin, birds, posts and more.",
        "title": "BirdAI API HFENGVNSIV",
        "termsOfService": "http://swagger.io/terms/",
        "contact": {
            "name": "Tovah Parnes",
            "email": "??"
        },
        "license": {
            "name": "MIT License",
            "url": "https://opensource.org/license/mit/"
        },
        "version": "2.0"
    },
    "host": "localhost:3300",
    "basePath": "/",
    "paths": {
        "/users/": {
            "post": {
                "description": "Get current user",
                "consumes": [
                    "application/json"
                ],
                "produces": [
                    "application/json"
                ],
                "tags": [
                    "users"
                ],
                "summary": "Get current user",
                "responses": {
                    "200": {
                        "description": "OK",
                        "schema": {
                            "allOf": [
                                {
                                    "$ref": "#/definitions/users.ResponseHTTP"
                                },
                                {
                                    "type": "object",
                                    "properties": {
                                        "data": {
                                            "type": "array",
                                            "items": {
                                                "$ref": "#/definitions/models.User"
                                            }
                                        }
                                    }
                                }
                            ]
                        }
                    },
                    "401": {
                        "description": "Unauthorized",
                        "schema": {
                            "$ref": "#/definitions/users.ResponseHTTP"
                        }
                    },
                    "404": {
                        "description": "Not Found",
                        "schema": {
                            "$ref": "#/definitions/users.ResponseHTTP"
                        }
                    },
                    "503": {
                        "description": "Service Unavailable",
                        "schema": {
                            "$ref": "#/definitions/users.ResponseHTTP"
                        }
                    }
                }
            }
        },
        "/users/set:{set}": {
            "get": {
                "description": "Get set of all users",
                "consumes": [
                    "application/json"
                ],
                "produces": [
                    "application/json"
                ],
                "tags": [
                    "users"
                ],
                "summary": "Get set of all users",
                "responses": {
                    "200": {
                        "description": "OK",
                        "schema": {
                            "allOf": [
                                {
                                    "$ref": "#/definitions/users.ResponseHTTP"
                                },
                                {
                                    "type": "object",
                                    "properties": {
                                        "data": {
                                            "type": "array",
                                            "items": {
                                                "$ref": "#/definitions/models.User"
                                            }
                                        }
                                    }
                                }
                            ]
                        }
                    },
                    "401": {
                        "description": "Unauthorized",
                        "schema": {
                            "$ref": "#/definitions/users.ResponseHTTP"
                        }
                    },
                    "406": {
                        "description": "Not Acceptable",
                        "schema": {
                            "$ref": "#/definitions/users.ResponseHTTP"
                        }
                    },
                    "503": {
                        "description": "Service Unavailable",
                        "schema": {
                            "$ref": "#/definitions/users.ResponseHTTP"
                        }
                    }
                }
            }
        },
        "/users/{id}": {
            "get": {
                "description": "Get user by ID",
                "consumes": [
                    "application/json"
                ],
                "produces": [
                    "application/json"
                ],
                "tags": [
                    "users"
                ],
                "summary": "Get user by ID",
                "parameters": [
                    {
                        "type": "integer",
                        "description": "Book ID",
                        "name": "id",
                        "in": "path",
                        "required": true
                    }
                ],
                "responses": {
                    "200": {
                        "description": "OK",
                        "schema": {
                            "allOf": [
                                {
                                    "$ref": "#/definitions/users.ResponseHTTP"
                                },
                                {
                                    "type": "object",
                                    "properties": {
                                        "data": {
                                            "type": "array",
                                            "items": {
                                                "$ref": "#/definitions/models.User"
                                            }
                                        }
                                    }
                                }
                            ]
                        }
                    },
                    "404": {
                        "description": "Not Found",
                        "schema": {
                            "$ref": "#/definitions/users.ResponseHTTP"
                        }
                    },
                    "503": {
                        "description": "Service Unavailable",
                        "schema": {
                            "$ref": "#/definitions/users.ResponseHTTP"
                        }
                    }
                }
            }
        }
    },
    "definitions": {
        "models.User": {
            "type": "object",
            "properties": {
                "_id": {
                    "type": "string"
                },
                "username": {
                    "type": "string"
                }
            }
        },
        "users.ResponseHTTP": {
            "type": "object",
            "properties": {
                "data": {},
                "message": {
                    "type": "string"
                },
                "success": {
                    "type": "boolean"
                }
            }
        }
    }
}